mathter/__init__.py
mathter/conversions.py
mathter-0.0.2.dist-info/LICENSE.txt
mathter-0.0.2.dist-info/METADATA
mathter-0.0.2.dist-info/WHEEL
mathter-0.0.2.dist-info/top_level.txt
mathter-0.0.2.dist-info/RECORD
