Metadata-Version: 2.1
Name: mathter
Version: 0.0.2
Summary: Math helper package
Home-page: https://github.com/gtwogood/mathter
Author: ctbaz
Author-email: curitibagarrett@gmail.com
License: UNKNOWN
Platform: UNKNOWN
Classifier: Programming Language :: Python :: 3
Classifier: License :: OSI Approved :: MIT License
Classifier: Operating System :: OS Independent
Requires-Python: >=3.6
